travers/__init__.py
travers/__version__.py
travers/errors.py
travers/xmler.py
travers/graphs/__init__.py
travers/graphs/graph.py
travers/graphs/graph_traversal.py
travers/graphs/internals.py
travers-0.1.11.dist-info/LICENSE
travers-0.1.11.dist-info/METADATA
travers-0.1.11.dist-info/NOTICE.md
travers-0.1.11.dist-info/WHEEL
travers-0.1.11.dist-info/top_level.txt
travers-0.1.11.dist-info/RECORD
