Metadata-Version: 2.1
Name: travers
Version: 0.1.11
Summary: Python Graph Library
Home-page: https://github.com/joocer/travers
Author: joocer
Author-email: justin.joyce@joocer.com
Maintainer: Joocer
License-File: LICENSE
License-File: NOTICE.md
Requires-Dist: orjson
